Workbook

Sheet Supuestos
A1: DATOS BASE DE LA EVALUACIÓN
A2: Precios de mercado investigados, horas registradas del proyecto y parámetros de funcionamiento del sistema.
A4: 1. BASE DE COSTEO DEL DESARROLLO
A5: Supuesto / Dato | B5: Valor | C5: Unidad | D5: Fuente / Justificación
A6: Horas hombre efectivas registradas al cierre del proyecto | B6: 658 | C6: HH | D6: Backlog_Sprint_Incremento_3.xlsx, hoja Backlog: 291 + 189 + 178 = 658 HH efectivas. La fila 184 omite la tarea de la fila 125.
A7: Integrantes considerados en evaluación original | B7: 7 | C7: personas | D7: Evaluación_ProyectoV2: equipo de desarrollo con 7 roles.
A8: Horas estándar por persona-mes | B8: 160 | C8: h/mes | D8: Supuesto operativo editable para convertir costo mensual a costo por hora.
A9: Costo empresa mensual del equipo original | B9: 11180000 | C9: CLP/mes | D9: Evaluación_ProyectoV2: suma mensual del costo empresa de los 7 roles.
A10: Costo hora interno ponderado | B10: =B9/(B7*B8) -> 9982.1429 | C10: CLP/HH | D10: Calculado desde costo empresa mensual / capacidad mensual total.
A12: 2. IMPLEMENTACIÓN, OPERACIÓN Y BENEFICIOS
A13: Supuesto / Dato | B13: Valor | C13: Unidad | D13: Fuente / Justificación
A14: Horas de configuración e instalación | B14: 12 | C14: HH | D14: Supuesto editable para instalación/configuración en la PyME.
A15: Horas de capacitación inicial | B15: 8 | C15: HH | D15: Supuesto editable para capacitación del dueño y trabajadores.
A16: Lector EAN-13 HID USB | B16: 50000 | C16: CLP | D16: Evaluación original: compra única del lector.
A17: Contingencia sobre costos iniciales | B17: 0.1 | C17: % | D17: Supuesto editable para imprevistos menores de implementación.
A18: Horas de soporte al mes | B18: 8 | C18: HH/mes | D18: Nuevo enfoque: soporte por bolsa de horas, en vez de media jornada fija.
A19: Costo nube mensual actual | B19: 0 | C19: CLP/mes | D19: Arquitectura actual acreditada con persistencia local; nube futura no se considera costo actual.
A20: Horizonte de evaluación | B20: 18 | C20: meses | D20: Se mantiene el horizonte de la evaluación inicial para comparabilidad.
A21: Tasa de descuento mensual | B21: 0.0096945159 | C21: % mensual | D21: Arrastrada desde la evaluación inicial (CAPM mensual). Actualizar si el profesor exige una tasa nueva.
A22: Beneficio mensual de la evaluación inicial | B22: 4000000 | C22: CLP/mes | D22: Evaluacion_ProyectoV2: beneficio mensual calculado en la primera evaluación económica.
A23: Porcentaje aplicado en la evaluación final | B23: 0.25 | C23: % | D23: Se considera el 25% del beneficio inicial para evaluar un ahorro mensual más moderado.
A24: Beneficio mensual estimado | B24: =B22*B23 -> 1000000 | C24: CLP/mes | D24: Beneficio inicial × porcentaje aplicado en la evaluación final.

Sheet Costos Iniciales
A1: COSTO INICIAL DEL SISTEMA
A2: El desarrollo se valoriza con las 658 HH efectivas registradas en el backlog final, en vez de 7 profesionales a jornada completa durante 4 meses.
A4: Concepto | B4: Cantidad | C4: Costo Unitario | D4: Costo Total | E4: Criterio
A5: Desarrollo del sistema | B5: =Supuestos!B6 -> 658 | C5: =Supuestos!B10 -> 9982.1429 | D5: =B5*C5 -> 6568250 | E5: HH efectivas registradas × costo hora interno de referencia
A6: Configuración e instalación | B6: =Supuestos!B14 -> 12 | C6: =Supuestos!B10 -> 9982.1429 | D6: =B6*C6 -> 119785.71 | E6: Horas de instalación × costo hora
A7: Capacitación inicial | B7: =Supuestos!B15 -> 8 | C7: =Supuestos!B10 -> 9982.1429 | D7: =B7*C7 -> 79857.143 | E7: Horas de capacitación × costo hora
A8: Hardware lector EAN-13 | B8: 1 | C8: =Supuestos!B16 -> 50000 | D8: =B8*C8 -> 50000 | E8: Compra única
A9: Subtotal antes de contingencia | D9: =SUM(D5:D8) -> 6817892.9 | E9: Suma de costos directos iniciales
A10: Contingencia | B10: =Supuestos!B17 -> 0.1 | D10: =D9*B10 -> 681789.29 | E10: % aplicado al subtotal inicial
A11: INVERSIÓN INICIAL ACTUALIZADA | D11: =D9+D10 -> 7499682.1 | E11: Costo total estimado de puesta en marcha
A13: Equivalente de esfuerzo | B13: =Supuestos!B6/Supuestos!B8 -> 4.1125 | C13: persona-mes | D13: =B13 -> 4.1125 | E13: HH desarrollo / 160 h por persona-mes
A15: Lectura metodológica
A16: Evaluación inicial | B16: 7 roles × 4 meses | E16: Asume 28 persona-mes de dedicación.
A17: Evaluación final | B17: 658 HH efectivas | E17: Equivale a 4,11 persona-mes usando 160 h/mes.
A18: Razón del cambio | E18: La nueva evaluación se alinea con el esfuerzo documentado en Scrum++ y con un proyecto personalizado para una sola PyME.

Sheet Operación
A1: COSTOS DE OPERACIÓN Y MANTENIMIENTO
A3: Concepto | B3: Cantidad | C3: Costo Unitario | D3: Costo Mensual | E3: Observación
A4: Soporte técnico | B4: =Supuestos!B18 -> 8 | C4: =Supuestos!B10 -> 9982.1429 | D4: =B4*C4 -> 79857.143 | E4: Bolsa mensual de horas; editable desde Supuestos.
A5: Infraestructura nube actual | B5: 1 | C5: =Supuestos!B19 -> 0 | D5: =B5*C5 -> 0 | E5: Persistencia local acreditada; costo mensual actual = 0.
A6: TOTAL OPERATIVO MENSUAL | D6: =SUM(D4:D5) -> 79857.143
A7: Costo operativo anual | B7: 12 | D7: =D6*B7 -> 958285.71 | E7: Costo mensual × 12
A8: Costo operativo horizonte | B8: =Supuestos!B20 -> 18 | D8: =D6*B8 -> 1437428.6 | E8: Costo mensual × horizonte de evaluación
A10: TCO — costo total de propiedad | D10: ='Costos Iniciales'!D11+D8 -> 8937110.7 | E10: Inversión inicial + costo operativo del horizonte

Sheet Flujo 18m
A1: FLUJO DE COSTOS Y BENEFICIOS A 18 MESES
A2: Los beneficios se calculan desde el valor mensual de la evaluación final; los costos iniciales y de operación se detallan en las hojas respectivas.
A4: Mes # | B4: Período | C4: Beneficio Bruto | D4: Costo Operativo | E4: Inversión Inicial | F4: Flujo Neto | G4: Flujo Descontado | H4: Acumulado Desc. | I4: Flag Payback
A5: 0 | B5: Mes 0 | C5: 0 | D5: 0 | E5: =-'Costos Iniciales'!D11 -> -7499682.1 | F5: =C5-D5+E5 -> -7499682.1 | G5: =F5 -> -7499682.1 | H5: =G5 -> -7499682.1 | I5: =IF(H5>=0,1,0) -> 0
A6: 1 | B6: Mes 1 | C6: =Supuestos!$B$24 -> 1000000 | D6: =Operación!$D$6 -> 79857.143 | E6: 0 | F6: =C6-D6+E6 -> 920142.86 | G6: =F6/(1+Supuestos!$B$21)^A6 -> 911308.17 | H6: =H5+G6 -> -6588374 | I6: =IF(H6>=0,1,0) -> 0
A7: 2 | B7: Mes 2 | C7: =Supuestos!$B$24 -> 1000000 | D7: =Operación!$D$6 -> 79857.143 | E7: 0 | F7: =C7-D7+E7 -> 920142.86 | G7: =F7/(1+Supuestos!$B$21)^A7 -> 902558.3 | H7: =H6+G7 -> -5685815.7 | I7: =IF(H7>=0,1,0) -> 0
A8: 3 | B8: Mes 3 | C8: =Supuestos!$B$24 -> 1000000 | D8: =Operación!$D$6 -> 79857.143 | E8: 0 | F8: =C8-D8+E8 -> 920142.86 | G8: =F8/(1+Supuestos!$B$21)^A8 -> 893892.45 | H8: =H7+G8 -> -4791923.2 | I8: =IF(H8>=0,1,0) -> 0
A9: 4 | B9: Mes 4 | C9: =Supuestos!$B$24 -> 1000000 | D9: =Operación!$D$6 -> 79857.143 | E9: 0 | F9: =C9-D9+E9 -> 920142.86 | G9: =F9/(1+Supuestos!$B$21)^A9 -> 885309.8 | H9: =H8+G9 -> -3906613.4 | I9: =IF(H9>=0,1,0) -> 0
A10: 5 | B10: Mes 5 | C10: =Supuestos!$B$24 -> 1000000 | D10: =Operación!$D$6 -> 79857.143 | E10: 0 | F10: =C10-D10+E10 -> 920142.86 | G10: =F10/(1+Supuestos!$B$21)^A10 -> 876809.55 | H10: =H9+G10 -> -3029803.9 | I10: =IF(H10>=0,1,0) -> 0
A11: 6 | B11: Mes 6 | C11: =Supuestos!$B$24 -> 1000000 | D11: =Operación!$D$6 -> 79857.143 | E11: 0 | F11: =C11-D11+E11 -> 920142.86 | G11: =F11/(1+Supuestos!$B$21)^A11 -> 868390.92 | H11: =H10+G11 -> -2161413 | I11: =IF(H11>=0,1,0) -> 0
A12: 7 | B12: Mes 7 | C12: =Supuestos!$B$24 -> 1000000 | D12: =Operación!$D$6 -> 79857.143 | E12: 0 | F12: =C12-D12+E12 -> 920142.86 | G12: =F12/(1+Supuestos!$B$21)^A12 -> 860053.12 | H12: =H11+G12 -> -1301359.8 | I12: =IF(H12>=0,1,0) -> 0
A13: 8 | B13: Mes 8 | C13: =Supuestos!$B$24 -> 1000000 | D13: =Operación!$D$6 -> 79857.143 | E13: 0 | F13: =C13-D13+E13 -> 920142.86 | G13: =F13/(1+Supuestos!$B$21)^A13 -> 851795.38 | H13: =H12+G13 -> -449564.46 | I13: =IF(H13>=0,1,0) -> 0
A14: 9 | B14: Mes 9 | C14: =Supuestos!$B$24 -> 1000000 | D14: =Operación!$D$6 -> 79857.143 | E14: 0 | F14: =C14-D14+E14 -> 920142.86 | G14: =F14/(1+Supuestos!$B$21)^A14 -> 843616.92 | H14: =H13+G14 -> 394052.46 | I14: =IF(H14>=0,1,0) -> 1
A15: 10 | B15: Mes 10 | C15: =Supuestos!$B$24 -> 1000000 | D15: =Operación!$D$6 -> 79857.143 | E15: 0 | F15: =C15-D15+E15 -> 920142.86 | G15: =F15/(1+Supuestos!$B$21)^A15 -> 835516.99 | H15: =H14+G15 -> 1229569.4 | I15: =IF(H15>=0,1,0) -> 1
A16: 11 | B16: Mes 11 | C16: =Supuestos!$B$24 -> 1000000 | D16: =Operación!$D$6 -> 79857.143 | E16: 0 | F16: =C16-D16+E16 -> 920142.86 | G16: =F16/(1+Supuestos!$B$21)^A16 -> 827494.83 | H16: =H15+G16 -> 2057064.3 | I16: =IF(H16>=0,1,0) -> 1
A17: 12 | B17: Mes 12 | C17: =Supuestos!$B$24 -> 1000000 | D17: =Operación!$D$6 -> 79857.143 | E17: 0 | F17: =C17-D17+E17 -> 920142.86 | G17: =F17/(1+Supuestos!$B$21)^A17 -> 819549.69 | H17: =H16+G17 -> 2876614 | I17: =IF(H17>=0,1,0) -> 1
... A23: 18 | B23: Mes 18 | C23: =Supuestos!$B$24 -> 1000000 | D23: =Operación!$D$6 -> 79857.143 | E23: 0 | F23: =C23-D23+E23 -> 920142.86 | G23: =F23/(1+Supuestos!$B$21)^A23 -> 773455.45 | H23: =H22+G23 -> 7631285.3 | I23: =IF(H23>=0,1,0) -> 1
A25: INDICADORES
A26: Indicador | B26: Valor | C26: Interpretación
A27: Inversión inicial actualizada | B27: ='Costos Iniciales'!D11 -> 7499682.1 | C27: Costo estimado de desarrollo + implementación.
A28: Costo operativo total 18m | B28: =Operación!D8 -> 1437428.6 | C28: Mantenimiento/operación durante el horizonte.
A29: Beneficio bruto total 18m | B29: =SUM(C6:C23) -> 18000000 | C29: Supuesto mensual utilizado × 18.
A30: VAN de la evaluación final | B30: =SUM(G5:G23) -> 7631285.3 | C30: Resultado de los flujos mensuales descontados menos la inversión inicial.
A31: TIR mensual | B31: =IRR(F5:F23) -> 0.10097189 | C31: Tasa que hace VAN = 0; comparar con tasa de descuento mensual.
A32: Payback descontado | B32: =IFERROR(MATCH(1,I5:I23,0)-1,"No recuperado") -> 9 | C32: Primer mes con acumulado descontado no negativo.

Sheet Escenarios
A1: RESULTADOS SEGÚN EL BENEFICIO MENSUAL
A2: Comparación del valor actual neto para distintos niveles de beneficio mensual durante 18 meses.
A4: Escenario | B4: % Beneficio Original | C4: Beneficio Mensual | D4: Costo Mensual | E4: Inversión Inicial | F4: VAN 18m | G4: ROI 18m | H4: Payback Simple (meses)
A5: Evaluación final | B5: 0.25 | C5: =Supuestos!$B$22*B5 -> 1000000 | D5: =Operación!$D$6 -> 79857.143 | E5: ='Costos Iniciales'!$D$11 -> 7499682.1 | F5: =-E5+(C5-D5)*((1-(1+Supuestos!$B$21)^(-Supuestos!$B$20))/Supuestos!$B$21) -> 7631285.3 | G5: =((C5*Supuestos!$B$20)-(D5*Supuestos!$B$20)-E5)/(E5+D5*Supuestos!$B$20) -> 1.0140737 | H5: =IF(C5<=D5,"No recuperado",E5/(C5-D5)) -> 8.1505628
A6: Moderado | B6: 0.5 | C6: =Supuestos!$B$22*B6 -> 2000000 | D6: =Operación!$D$6 -> 79857.143 | E6: ='Costos Iniciales'!$D$11 -> 7499682.1 | F6: =-E6+(C6-D6)*((1-(1+Supuestos!$B$21)^(-Supuestos!$B$20))/Supuestos!$B$21) -> 24075436 | G6: =((C6*Supuestos!$B$20)-(D6*Supuestos!$B$20)-E6)/(E6+D6*Supuestos!$B$20) -> 3.0281475 | H6: =IF(C6<=D6,"No recuperado",E6/(C6-D6)) -> 3.9057938
A7: Alto | B7: 0.75 | C7: =Supuestos!$B$22*B7 -> 3000000 | D7: =Operación!$D$6 -> 79857.143 | E7: ='Costos Iniciales'!$D$11 -> 7499682.1 | F7: =-E7+(C7-D7)*((1-(1+Supuestos!$B$21)^(-Supuestos!$B$20))/Supuestos!$B$21) -> 40519586 | G7: =((C7*Supuestos!$B$20)-(D7*Supuestos!$B$20)-E7)/(E7+D7*Supuestos!$B$20) -> 5.0422212 | H7: =IF(C7<=D7,"No recuperado",E7/(C7-D7)) -> 2.5682586
A8: Evaluación inicial | B8: 1 | C8: =Supuestos!$B$22*B8 -> 4000000 | D8: =Operación!$D$6 -> 79857.143 | E8: ='Costos Iniciales'!$D$11 -> 7499682.1 | F8: =-E8+(C8-D8)*((1-(1+Supuestos!$B$21)^(-Supuestos!$B$20))/Supuestos!$B$21) -> 56963736 | G8: =((C8*Supuestos!$B$20)-(D8*Supuestos!$B$20)-E8)/(E8+D8*Supuestos!$B$20) -> 7.056295 | H8: =IF(C8<=D8,"No recuperado",E8/(C8-D8)) -> 1.9131145

Sheet Comparación
A1: COMPARACIÓN — EVALUACIÓN INICIAL VS. ACTUALIZADA
A2: La evaluación final utiliza 658 HH efectivas, 8 horas de soporte al mes y un beneficio mensual equivalente al 25% del cálculo inicial.
A4: Indicador | B4: Evaluación Inicial | C4: Evaluación Actualizada | D4: Variación | E4: Comentario
A5: Base de desarrollo | B5: 7 roles × 4 meses | C5: 658 HH efectivas | D5: — | E5: Cambia la unidad de costeo desde dotación fija a esfuerzo del proyecto.
A6: Costo desarrollo / RRHH | B6: 44720000 | C6: ='Costos Iniciales'!D5 -> 6568250 | D6: =IFERROR((C6-B6)/B6,"—") -> -0.853125 | E6: Inicial: equipo full-time. Final: HH efectivas × costo hora de referencia.
A7: Inversión inicial total | B7: 44770000 | C7: ='Costos Iniciales'!D11 -> 7499682.1 | D7: =IFERROR((C7-B7)/B7,"—") -> -0.8324842 | E7: Incluye hardware e implementación.
A8: Costo operativo mensual | B8: 780000 | C8: =Operación!D6 -> 79857.143 | D8: =IFERROR((C8-B8)/B8,"—") -> -0.89761905 | E8: Inicial: media jornada fija. Actualizada: bolsa de 8 HH/mes.
A9: Costo operativo 18m | B9: 14040000 | C9: =Operación!D8 -> 1437428.6 | D9: =IFERROR((C9-B9)/B9,"—") -> -0.89761905 | E9: Horizonte comparable de 18 meses.
A10: TCO 18m | B10: 58810000 | C10: =Operación!D10 -> 8937110.7 | D10: =IFERROR((C10-B10)/B10,"—") -> -0.84803417 | E10: Inversión inicial + operación del horizonte.
A11: Beneficio mensual referencia | B11: 4000000 | C11: =Supuestos!B24 -> 1000000 | D11: =IFERROR((C11-B11)/B11,"—") -> -0.75 | E11: La evaluación final considera $1.000.000 mensuales.
A12: VAN 18m | B12: 8180163.9 | C12: ='Flujo 18m'!B30 -> 7631285.3 | D12: =IFERROR((C12-B12)/B12,"—") -> -0.067098731 | E12: Los beneficios mensuales son distintos entre ambas evaluaciones.
A13: Payback descontado (meses) | B13: 16 | C13: ='Flujo 18m'!B32 -> 9 | D13: =IFERROR(C13-B13,"—") -> -7 | E13: Primer mes con acumulado descontado positivo.

Sheet Fuentes
A1: TRAZABILIDAD DE DATOS Y FUENTES
A3: Dato utilizado | B3: Valor / Referencia | C3: Fuente | D3: Ubicación / Nota
A4: Exigencia de estimación de costos y beneficios | B4: Obligatoria | C4: 2026-Rubrica Proyecto-Ingenieria_de_Software-v5.pdf | D4: Pág. 1: anexo incluye Planificación, Estimación de Costos y Beneficios.
A5: Excel de costo-beneficio en incrementos | B5: Debe acompañar las entregas | C5: 2026-Rubrica Proyecto-Ingenieria_de_Software-v5.pdf | D5: Pág. 9: Excel de estimación de costo y beneficio aplica también a incrementos Scrum++.
A6: Horas del proyecto | B6: 658 HH efectivas | C6: Backlog_Sprint_Incremento_3.xlsx | D6: Hoja Backlog: filas 3:53 = 291 HH, 56:120 = 189 HH, 125:183 = 178 HH. Total 658 HH efectivas.
A7: Incremento 3 | B7: 173 HH estimadas / 178 HH efectivas | C7: Backlog_Sprint_Incremento_3.xlsx | D7: Hoja Backlog, filas 125:183. La fórmula de la fila 184 comienza en 126 y omite la tarea de la fila 125.
A8: Arquitectura operativa | B8: Persistencia local libSQL | C8: Grupo 6 - Incremento 3 (1).docx | D8: Vista física: nube/sincronización futura, no acreditada como costo actual.
A9: Costo empresa mensual equipo | B9: $11.180.000 | C9: Evaluacion_ProyectoV2 (1) (1).xlsx | D9: Hoja Costos RRHH: suma mensual de 7 roles.
A10: Lector EAN-13 | B10: $50.000 | C10: Evaluacion_ProyectoV2 (1) (1).xlsx | D10: Hoja Licencias y Herramientas / Inversión Inicial.
A12: CRITERIO METODOLÓGICO
A13: 1 | B13: El costo actualizado no supone siete contrataciones full-time por cuatro meses.
A14: 2 | B14: Las 658 HH efectivas se valorizan con una tarifa derivada del modelo salarial inicial.
A15: 3 | B15: La mantención se modela como bolsa de horas mensual, adecuada para una PyME con aplicación local.
A16: 4 | B16: El beneficio mensual final es $1.000.000: 25% de los $4.000.000 de la primera evaluación.

Sheet Resumen
A1: EVALUACIÓN FINAL DE COSTOS Y BENEFICIOS
A2: Sistema Integral de Gestión Operativa del Minimarket y Panadería Huáscar | 658 HH efectivas | Beneficio mensual estimado: $1.000.000
A4: INVERSIÓN INICIAL | C4: COSTO MENSUAL | E4: TCO 18 MESES | G4: VAN 18 MESES
A5: ='Costos Iniciales'!D11 -> 7499682.1 | C5: =Operación!D6 -> 79857.143 | E5: =Operación!D10 -> 8937110.7 | G5: ='Flujo 18m'!B30 -> 7631285.3
A8: RESUMEN DEL CÁLCULO
A9: Elemento | B9: Antes | C9: Ahora | D9: Impacto
A10: Costo de desarrollo | B10: 7 roles × 4 meses | C10: 658 HH efectivas | D10: Trazabilidad con las horas registradas de los tres incrementos
A11: Soporte | B11: 1 dev Jr media jornada | C11: 8 horas de soporte al mes | D11: Costo de mantenimiento mensual
A12: Nube | B12: Servicio de nube en evaluación inicial | C12: Almacenamiento local: $0 al mes | D12: Sin pago mensual de nube
A13: Beneficios | B13: $4.000.000/mes en la primera evaluación | C13: $1.000.000/mes en la evaluación final | D13: 25% del cálculo inicial
A15: COMPARACIÓN ECONÓMICA PRINCIPAL
A16: Indicador | B16: Inicial | C16: Final | E16: Conclusión: La evaluación final usa las 658 horas efectivas registradas en el backlog y los precios de mercado investigados para el proyecto. La inversión inicial se estima en $7.499.682 y el costo operativo mensual en $79.857. Con un beneficio estimado de $1.000.000 al mes, el VAN a 18 meses es $7.631.285.
A17: Inversión inicial | B17: 44770000 | C17: ='Costos Iniciales'!D11 -> 7499682.1
A18: Costo operativo mensual | B18: 780000 | C18: =Operación!D6 -> 79857.143
A19: Costo operativo 18m | B19: 14040000 | C19: =Operación!D8 -> 1437428.6
A20: TCO 18m | B20: 58810000 | C20: =Operación!D10 -> 8937110.7
