Workbook

Sheet Resumen Ejecutivo
A1: EVALUACIÓN DE PROYECTO — SISTEMA DE GESTIÓN DE INVENTARIO Y PERSONAL
A2: Minimarket y Panadería Huáscar — Rengo, Región de O'Higgins — Horizonte de análisis: 18 meses
A4: SUPUESTOS PRINCIPALES
A5: Concepto | B5: Valor | C5: Fuente / Observación
A6: Tasa de descuento mensual (CAPM) | B6: ='Supuestos y CAPM'!B15 -> 0.0096945159 | C6: Calculada por CAPM — ver hoja 'Supuestos y CAPM'
A7: Tasa de descuento anual (CAPM) | B7: ='Supuestos y CAPM'!B14 -> 0.122742 | C7: CAPM = Rf + β × (Rm - Rf), Chile 2026
A8: Período de desarrollo (meses) | B8: 4 | C8: Período durante el cual se desarrolla el sistema antes de la puesta en marcha
A9: Horizonte de análisis (meses) | B9: 18 | C9: Análisis de flujo de caja a 1 año calendario
A10: Beneficio mensual estimado (CLP) | B10: 4000000 | C10: Ahorro por automatización + reducción 4% robos (ver Documento 0, §5)
A12: INDICADORES FINANCIEROS (HORIZONTE 18 MESES)
A13: Indicador | B13: Valor | C13: Interpretación
A14: Inversión Inicial Total (CLP) | B14: ='Inversión Inicial'!B11 -> 44770000 | C14: RRHH desarrollo (4 meses) + Hardware + Setup inicial
A15: Costo Operativo Mensual (CLP) | B15: ='Inversión Inicial'!B18 -> 780000 | C15: Soporte técnico post-implementación + GitHub Team
A16: Flujo Neto Mensual (CLP) | B16: =B10-B15 -> 3220000 | C16: Beneficio - Costo operativo
A17: Valor Actual Neto (VAN) | B17: ='Flujo de Caja'!B28 -> 8180163.9 | C17: VAN > 0 → proyecto crea valor
A18: Tasa Interna de Retorno (TIR) mensual | B18: ='Flujo de Caja'!B29 -> 0.028718396 | C18: TIR > tasa descuento → proyecto viable
A19: TIR anualizada equivalente | B19: =(1+B18)^12-1 -> 0.40461749 | C19: TIR mensual llevada a base anual compuesta
A20: Retorno sobre Inversión (ROI 18 meses) | B20: =(B10*18-B15*18-B14)/B14 -> 0.29461693 | C20: (Beneficios netos 18m - Inversión) / Inversión
A21: Período de recuperación (meses) | B21: ='Flujo de Caja'!B30 -> Al mes 16 comienza a recuperar | C21: Meses para que el flujo acumulado descontado sea positivo
A23: NOTA METODOLÓGICA
A24: La tasa de descuento se calcula mediante el modelo CAPM con datos reales del mercado chileno a abril de 2026: tasa libre de riesgo del bono BTP a 10 años del Banco Central, beta del sector Software (System & Application) de Damodaran, y rendimiento esperado del IPSA basado en su promedio histórico de largo plazo. Los sueldos reflejan valores de mercado IT Chile 2026 según guías de IT Hunters, Glassdoor y Computrabajo. El stack tecnológico es 100% open-source (MIT, Apache 2.0, Public Domain); los únicos costos monetarios son GitHub Team ($4 USD/usuario/mes) y el hardware lector EAN-13. El beneficio mensual de $4.000.000 refleja: reducción de 4% en robos (Doc. 0 §5), ahorro en tiempo de inventario manual, reducción de mermas por vencimiento y mejor toma de decisiones.
A26: BIBLIOGRAFÍA / FUENTES CONSULTADAS
A27: Concepto / Dato | B27: Fuente | C27: URL
A28: Rf — Tasa libre de riesgo (BTP-10 Chile) | B28: Tradingeconomics — Chile 10-Year Government Bond Yield | C28: https://tradingeconomics.com/chile/government-bond-yield
A29: Rf — Tasa libre de riesgo (BTP-10 Chile, en español) | B29: Tradingeconomics — Rendimiento de bonos Chile a 10 años | C29: https://es.tradingeconomics.com/chile/government-bond-yield
A30: Rf — Datos históricos BTP-10 Banco Central de Chile | B30: Banco Central de Chile — Base de Datos Estadísticos | C30: https://si3.bcentral.cl/Siete/ES/Siete/Cuadro/CAP_DYB/MN_ESTAD_MON55/EM_OMA_BTP10/E6212c
A31: β — Beta sector Software (System & Application) | B31: Aswath Damodaran (NYU Stern) — Betas by Sector, enero 2026 | C31: https://pages.stern.nyu.edu/~adamodar/New_Home_Page/datafile/Betas.html
A32: Rm — Rentabilidad IPSA 2025 (56,81%) y proyecciones 2026 | B32: La Tercera — Pulso, enero 2026 | C32: https://www.latercera.com/pulso/noticia/donde-invertir-en-2026-siete-expertos-dan-las-claves-en-acciones-deuda-y-la-inteligencia-artificial/
A33: Rm — Rendimiento IPSA 2025 (cierre) | B33: Emol — Resultados bolsa IPSA Chile 2025 | C33: https://www.emol.com/noticias/Economia/2025/12/24/1186805/resultados-bolsa-ipsa-chile.html
A34: Rm — Ficha técnica índice IPSA | B34: S&P Dow Jones Indices — S&P IPSA | C34: https://www.spglobal.com/spdji/en/indices/equity/sp-ipsa/
A35: Sueldos IT Chile 2026 — Guía por rol y seniority | B35: CATED — Guía Sueldos Programador Chile 2026 | C35: https://cated.cl/guia-sueldos
A36: Sueldos IT Chile 2026 — Medianas por cargo | B36: Computrabajo Chile — Salarios Developer 2026 | C36: https://cl.computrabajo.com/salarios/developer
A37: Sueldos IT Chile 2026 — Rangos Santiago | B37: Glassdoor Chile — Software Developer Santiago | C37: https://www.glassdoor.com.mx/Sueldos/santiago-chile-software-developer-sueldo-SRCH_IL.0,14_IM1004_KO15,33.htm
A38: Banco Central de Chile — TPM y tasas de referencia | B38: Banco Central de Chile — Estadísticas | C38: https://www.bcentral.cl/areas/estadisticas
A39: Tipo de cambio CLP/USD | B39: Banco Central de Chile — Estadísticas cambiarias | C39: https://www.bcentral.cl/

Sheet Supuestos y CAPM
A1: CÁLCULO DE LA TASA DE DESCUENTO — MODELO CAPM
A2: CAPM: R = Rf + β × (Rm − Rf)
A4: PARÁMETROS CAPM (MERCADO CHILENO, ABRIL 2026)
A5: Parámetro | B5: Valor | C5: Fuente
A6: Rf — Tasa libre de riesgo (anual) | B6: 0.0546 | C6: BTP-10 Chile, rendimiento marzo 2026 (5,46%) — Tradingeconomics / Banco Central de Chile
A7: β — Beta desapalancado sector Software (System & Application) | B7: 1.23 | C7: Aswath Damodaran — Betas by Sector, enero 2026 (309 empresas, unlevered beta)
A8: Rm — Rentabilidad esperada del mercado (IPSA) | B8: 0.11 | C8: Promedio histórico IPSA de largo plazo (~10–12%). 2025 fue atípico (56,8%); se usa valor conservador
A10: Premio por riesgo de mercado (Rm − Rf) | B10: =B8-B6 -> 0.0554 | C10: Diferencia entre rentabilidad esperada del mercado y tasa libre de riesgo
A11: Premio ajustado por β: β × (Rm − Rf) | B11: =B7*B10 -> 0.068142 | C11: Premio por riesgo sistemático ajustado al sector software
A13: RESULTADO CAPM
A14: Tasa de descuento ANUAL (CAPM) | B14: =B6+B7*(B8-B6) -> 0.122742 | C14: R = Rf + β × (Rm − Rf)
A15: Tasa de descuento MENSUAL equivalente | B15: =(1+B14)^(1/12)-1 -> 0.0096945159 | C15: Conversión anual → mensual compuesta: (1+R_anual)^(1/12) − 1
A17: OTROS PARÁMETROS DEL PROYECTO
A18: Parámetro | B18: Valor | C18: Fuente / Observación
A19: Tipo de cambio CLP/USD (referencia abril 2026) | B19: 920 | C19: Tipo de cambio observado abril 2026 — Banco Central de Chile
A20: Factor costo indirecto (sobre sueldo bruto) | B20: 0.3 | C20: AFP 11,5% + Salud 7% + Seguro Cesantía 0,6% + Mutual + Administración ≈ 30%
A21: Factor líquido → bruto (sueldo) | B21: 1.25 | C21: Relación aproximada bruto/líquido considerando descuentos previsionales e impuesto único
A22: Ingresos mensuales Minimarket (CLP) | B22: 40000000 | C22: Documento 0, §5: ventas aprox. $40M/mes
A23: Pérdidas mensuales estimadas por robos (% ventas) | B23: 0.04 | C23: Documento 0, §5: 3,5%-4,5% (usamos 4% como base)
A25: NOTA SOBRE EL CÁLCULO CAPM
A26: El modelo CAPM (Capital Asset Pricing Model, Sharpe 1964) determina la rentabilidad mínima exigida a un proyecto en función de su riesgo sistemático. Aplicado a este proyecto: • Rf (5,46%): rendimiento del bono BTP a 10 años del Banco Central de Chile (marzo 2026). Se elige la curva nominal en pesos porque el flujo de caja está en CLP nominales. • β (1,23): beta desapalancado (unlevered) del sector 'Software (System & Application)' reportado por Damodaran (enero 2026, 309 empresas). Se usa unlevered beta por ser la métrica adecuada para evaluar un proyecto sin estructura de capital definida. • Rm (11,0%): rendimiento esperado del IPSA usando promedio histórico conservador. 2025 registró +56,81% (atípico); se usa 11% como proxy de largo plazo ajustado. Resultado: tasa de descuento anual de aprox. 12,3%, equivalente a ~0,97% mensual. Esta tasa supera la tasa libre de riesgo, reflejando adecuadamente el riesgo incremental del proyecto.

Sheet Costos RRHH
A1: COSTOS DE RECURSOS HUMANOS — EQUIPO DE DESARROLLO (4 MESES)
A2: Sueldos de mercado IT Chile 2026 — fuentes: XIII Guía IT Hunters 2026, Glassdoor, CATED, Computrabajo
A4: Rol | B4: Cantidad | C4: Sueldo Líquido (CLP) | D4: Sueldo Bruto (CLP) | E4: Costo Empresa (Bruto + 30%) (CLP) | F4: Costo Total 4 Meses (CLP) | G4: Observación / Fuente
A5: Líder de Proyecto (Junior) | B5: 1 | C5: 1120000 | D5: 1400000 | E5: =D5*(1+'Supuestos y CAPM'!$B$20) -> 1820000 | F5: =B5*E5*'Resumen Ejecutivo'!$B$8 -> 7280000 | G5: PM recién titulado — IT Hunters 2026 Jr: $1,2M–$1,5M bruto
A6: Arquitecto de Software (Junior) | B6: 1 | C6: 1120000 | D6: 1400000 | E6: =D6*(1+'Supuestos y CAPM'!$B$20) -> 1820000 | F6: =B6*E6*'Resumen Ejecutivo'!$B$8 -> 7280000 | G6: Architect Jr recién titulado — CATED 2026 Jr: $1,2M–$1,5M bruto
A7: Desarrollador Backend (Junior) | B7: 1 | C7: 960000 | D7: 1200000 | E7: =D7*(1+'Supuestos y CAPM'!$B$20) -> 1560000 | F7: =B7*E7*'Resumen Ejecutivo'!$B$8 -> 6240000 | G7: Node.js/Express Jr recién titulado — CATED 2026 Jr: $900K–$1,4M
A8: Desarrollador Frontend (Junior) | B8: 1 | C8: 960000 | D8: 1200000 | E8: =D8*(1+'Supuestos y CAPM'!$B$20) -> 1560000 | F8: =B8*E8*'Resumen Ejecutivo'!$B$8 -> 6240000 | G8: React/TypeScript Jr recién titulado — CATED 2026 Jr: $900K–$1,4M
A9: Ingeniero DevOps (Junior) | B9: 1 | C9: 1040000 | D9: 1300000 | E9: =D9*(1+'Supuestos y CAPM'!$B$20) -> 1690000 | F9: =B9*E9*'Resumen Ejecutivo'!$B$8 -> 6760000 | G9: DevOps Jr recién titulado — IT Hunters 2026 Jr: $1,1M–$1,4M
A10: Ingeniero QA (Junior) | B10: 1 | C10: 800000 | D10: 1000000 | E10: =D10*(1+'Supuestos y CAPM'!$B$20) -> 1300000 | F10: =B10*E10*'Resumen Ejecutivo'!$B$8 -> 5200000 | G10: QA Jr recién titulado — Glassdoor Chile 2026 Jr: $900K–$1,2M
A11: Analista de Negocio (Junior) | B11: 1 | C11: 880000 | D11: 1100000 | E11: =D11*(1+'Supuestos y CAPM'!$B$20) -> 1430000 | F11: =B11*E11*'Resumen Ejecutivo'!$B$8 -> 5720000 | G11: Business Analyst Jr recién titulado — IT Hunters 2026 Jr: $1M–$1,3M
A12: TOTAL INVERSIÓN RRHH (4 meses desarrollo) | B12: =SUM(B5:B11) -> 7 | C12: — | D12: — | E12: =SUMPRODUCT(B5:B11,E5:E11) -> 11180000 | F12: =SUM(F5:F11) -> 44720000 | G12: Suma de costos totales del equipo durante los 4 meses de desarrollo
A14: NOTA: El costo empresa incluye 30% de cargas sociales e indirectos (AFP 11,5% + Salud 7% + Seguro Cesantía 0,6% + Mutual + administración), según legislación laboral chilena. El sueldo bruto se deriva del líquido aplicando factor 1,25x (ver 'Supuestos y CAPM' celda B21). Fuentes: XIII Guía Salarial IT 2026 (IT Hunters, 105.000+ CVs), Glassdoor Chile marzo 2026, CATED Guía Sueldos 2026, Computrabajo Chile 2026.

Sheet Licencias y Herramientas
A1: LICENCIAS, DEPENDENCIAS Y HERRAMIENTAS — DIMENSIÓN TÉCNICA
A2: Listado completo de componentes del stack — incluye licencias gratuitas (open source)
A4: Componente | B4: Categoría | C4: Versión | D4: Tipo Licencia | E4: Costo Único (CLP) | F4: Costo Mensual (CLP) | G4: Función / Referencia
A5: React | B5: Frontend | C5: 19.2.5 | D5: MIT (Gratis) | E5: 0 | F5: 0 | G5: Biblioteca UI declarativa — react.dev
A6: TypeScript | B6: Frontend | C6: 6.0.3 | D6: Apache 2.0 (Gratis) | E6: 0 | F6: 0 | G6: Superconjunto tipado de JavaScript — typescriptlang.org
A7: electron-vite | B7: Build Tool | C7: 5.0.0 | D7: MIT (Gratis) | E7: 0 | F7: 0 | G7: Build unificado main/preload/renderer con HMR — electron-vite.org
A8: shadcn/ui | B8: Frontend UI | C8: 4.3.1 | D8: MIT (Gratis) | E8: 0 | F8: 0 | G8: Componentes accesibles sobre Radix UI — ui.shadcn.com
A9: Tailwind CSS | B9: Frontend CSS | C9: 4.2.4 | D9: MIT (Gratis) | E9: 0 | F9: 0 | G9: Framework CSS utility-first — tailwindcss.com
A10: Recharts | B10: Frontend Charts | C10: 3.8.1 | D10: MIT (Gratis) | E10: 0 | F10: 0 | G10: Gráficos SVG para React (RF46) — recharts.org
A11: Node.js LTS | B11: Backend Runtime | C11: 24.15.0 | D11: MIT (Gratis) | E11: 0 | F11: 0 | G11: Runtime JavaScript embebido en Electron
A12: Express | B12: Backend Framework | C12: 5.2.1 | D12: MIT (Gratis) | E12: 0 | F12: 0 | G12: Framework HTTP minimalista — expressjs.com
A13: jsonwebtoken (JWT) | B13: Autenticación | C13: 9.0.3 | D13: MIT (Gratis) | E13: 0 | F13: 0 | G13: Gestión de sesiones RFC 7519 (RF55)
A14: bcryptjs | B14: Seguridad | C14: 3.0.3 | D14: MIT (Gratis) | E14: 0 | F14: 0 | G14: Hashing de contraseñas con sal (RNF04)
A15: libSQL | B15: Base de Datos | C15: 0.17.2 | D15: MIT (Gratis) | E15: 0 | F15: 0 | G15: Fork open source de SQLite con replicación nativa — turso.tech
A16: @libsql/client | B16: DB Binding | C16: 0.17.2 | D16: MIT (Gratis) | E16: 0 | F16: 0 | G16: Cliente oficial libSQL con sync engine de embedded replicas
... A31: Soporte Técnico Post-Implementación | B31: Operación | C31: — | D31: 1 dev Jr media jornada | E31: 0 | F31: 780000 | G31: Mantención correctiva y evolutiva (1 dev Junior × 50% dedicación)
A32: TOTALES | B32: — | C32: — | D32: — | E32: =SUM(E5:E31) -> 50000 | F32: =SUM(F5:F31) -> 780000

Sheet Inversión Inicial
A1: INVERSIÓN INICIAL Y COSTOS OPERATIVOS
A3: INVERSIÓN INICIAL (PERÍODO 0)
A4: Concepto | B4: Monto (CLP) | C4: Observación
A5: Costos RRHH (equipo desarrollo × 4 meses) | B5: ='Costos RRHH'!F12 -> 44720000 | C5: Total costo empresa del equipo completo durante desarrollo
A6: Hardware: Lector EAN-13 HID USB | B6: ='Licencias y Herramientas'!E30 -> 50000 | C6: Compra única del lector de código de barras
A7: Setup infraestructura (Cloudflare R2, GitHub repos) | B7: 0 | C7: Configuración inicial sin costo (tier gratuito + plan Team ya contabilizado)
A8: Capacitación inicial usuarios (dueño + cajeros) | B8: 0 | C8: Asumida dentro del rol del Analista de Negocio (documentación y entrega)
A10: Subtotal Licencias + Hardware | B10: =SUM(B6:B8) -> 50000
A11: INVERSIÓN TOTAL INICIAL | B11: =B5+B10 -> 44770000
A14: COSTOS OPERATIVOS MENSUALES (POST-IMPLEMENTACIÓN)
A15: Concepto | B15: Monto Mensual (CLP) | C15: Observación
A16: Soporte técnico (1 dev media jornada) | B16: ='Licencias y Herramientas'!F31 -> 780000 | C16: Mantención correctiva y evolutiva post-implementación
A17: Infraestructura nube (Cloudflare R2) | B17: 0 | C17: Tier gratuito cubre uso del proyecto (≤350 MB/mes vs 10 GB disponibles)
A18: COSTO OPERATIVO MENSUAL TOTAL | B18: =SUM(B16:B17) -> 780000

Sheet Flujo de Caja
A1: FLUJO DE CAJA PROYECTADO — HORIZONTE 18 MESES
A2: Tasa de descuento: CAPM mensual (ver 'Supuestos y CAPM') | Inversión inicial en Período 0
A4: Período | B4: Beneficio Bruto (CLP) | C4: Costo Operativo (CLP) | D4: Inversión (CLP) | E4: Flujo Neto (CLP) | F4: Flujo Descontado (CLP) | G4: Flujo Acumulado Desc. (CLP)
A5: Mes 0 | B5: 0 | C5: 0 | D5: =-'Inversión Inicial'!B11 -> -44770000 | E5: =B5+C5+D5 -> -44770000 | F5: =E5 -> -44770000 | G5: =F5 -> -44770000
A6: Mes 1 | B6: ='Resumen Ejecutivo'!$B$10 -> 4000000 | C6: =-'Inversión Inicial'!$B$18 -> -780000 | D6: 0 | E6: =B6+C6+D6 -> 3220000 | F6: =E6/(1+'Supuestos y CAPM'!$B$15)^1 -> 3189083.4 | G6: =G5+F6 -> -41580917
A7: Mes 2 | B7: ='Resumen Ejecutivo'!$B$10 -> 4000000 | C7: =-'Inversión Inicial'!$B$18 -> -780000 | D7: 0 | E7: =B7+C7+D7 -> 3220000 | F7: =E7/(1+'Supuestos y CAPM'!$B$15)^2 -> 3158463.6 | G7: =G6+F7 -> -38422453
A8: Mes 3 | B8: ='Resumen Ejecutivo'!$B$10 -> 4000000 | C8: =-'Inversión Inicial'!$B$18 -> -780000 | D8: 0 | E8: =B8+C8+D8 -> 3220000 | F8: =E8/(1+'Supuestos y CAPM'!$B$15)^3 -> 3128137.8 | G8: =G7+F8 -> -35294315
A9: Mes 4 | B9: ='Resumen Ejecutivo'!$B$10 -> 4000000 | C9: =-'Inversión Inicial'!$B$18 -> -780000 | D9: 0 | E9: =B9+C9+D9 -> 3220000 | F9: =E9/(1+'Supuestos y CAPM'!$B$15)^4 -> 3098103.2 | G9: =G8+F9 -> -32196212
A10: Mes 5 | B10: ='Resumen Ejecutivo'!$B$10 -> 4000000 | C10: =-'Inversión Inicial'!$B$18 -> -780000 | D10: 0 | E10: =B10+C10+D10 -> 3220000 | F10: =E10/(1+'Supuestos y CAPM'!$B$15)^5 -> 3068357 | G10: =G9+F10 -> -29127855
A11: Mes 6 | B11: ='Resumen Ejecutivo'!$B$10 -> 4000000 | C11: =-'Inversión Inicial'!$B$18 -> -780000 | D11: 0 | E11: =B11+C11+D11 -> 3220000 | F11: =E11/(1+'Supuestos y CAPM'!$B$15)^6 -> 3038896.3 | G11: =G10+F11 -> -26088959
A12: Mes 7 | B12: ='Resumen Ejecutivo'!$B$10 -> 4000000 | C12: =-'Inversión Inicial'!$B$18 -> -780000 | D12: 0 | E12: =B12+C12+D12 -> 3220000 | F12: =E12/(1+'Supuestos y CAPM'!$B$15)^7 -> 3009718.6 | G12: =G11+F12 -> -23079240
A13: Mes 8 | B13: ='Resumen Ejecutivo'!$B$10 -> 4000000 | C13: =-'Inversión Inicial'!$B$18 -> -780000 | D13: 0 | E13: =B13+C13+D13 -> 3220000 | F13: =E13/(1+'Supuestos y CAPM'!$B$15)^8 -> 2980821 | G13: =G12+F13 -> -20098419
A14: Mes 9 | B14: ='Resumen Ejecutivo'!$B$10 -> 4000000 | C14: =-'Inversión Inicial'!$B$18 -> -780000 | D14: 0 | E14: =B14+C14+D14 -> 3220000 | F14: =E14/(1+'Supuestos y CAPM'!$B$15)^9 -> 2952200.8 | G14: =G13+F14 -> -17146218
A15: Mes 10 | B15: ='Resumen Ejecutivo'!$B$10 -> 4000000 | C15: =-'Inversión Inicial'!$B$18 -> -780000 | D15: 0 | E15: =B15+C15+D15 -> 3220000 | F15: =E15/(1+'Supuestos y CAPM'!$B$15)^10 -> 2923855.4 | G15: =G14+F15 -> -14222363
A16: Mes 11 | B16: ='Resumen Ejecutivo'!$B$10 -> 4000000 | C16: =-'Inversión Inicial'!$B$18 -> -780000 | D16: 0 | E16: =B16+C16+D16 -> 3220000 | F16: =E16/(1+'Supuestos y CAPM'!$B$15)^11 -> 2895782.2 | G16: =G15+F16 -> -11326581
A17: Mes 12 | B17: ='Resumen Ejecutivo'!$B$10 -> 4000000 | C17: =-'Inversión Inicial'!$B$18 -> -780000 | D17: 0 | E17: =B17+C17+D17 -> 3220000 | F17: =E17/(1+'Supuestos y CAPM'!$B$15)^12 -> 2867978.6 | G17: =G16+F17 -> -8458602
A18: Mes 13 | B18: ='Resumen Ejecutivo'!$B$10 -> 4000000 | C18: =-'Inversión Inicial'!$B$18 -> -780000 | D18: 0 | E18: =B18+C18+D18 -> 3220000 | F18: =E18/(1+'Supuestos y CAPM'!$B$15)^13 -> 2840441.9 | G18: =G17+F18 -> -5618160.2
A19: Mes 14 | B19: ='Resumen Ejecutivo'!$B$10 -> 4000000 | C19: =-'Inversión Inicial'!$B$18 -> -780000 | D19: 0 | E19: =B19+C19+D19 -> 3220000 | F19: =E19/(1+'Supuestos y CAPM'!$B$15)^14 -> 2813169.5 | G19: =G18+F19 -> -2804990.6
A20: Mes 15 | B20: ='Resumen Ejecutivo'!$B$10 -> 4000000 | C20: =-'Inversión Inicial'!$B$18 -> -780000 | D20: 0 | E20: =B20+C20+D20 -> 3220000 | F20: =E20/(1+'Supuestos y CAPM'!$B$15)^15 -> 2786159.1 | G20: =G19+F20 -> -18831.547
A21: Mes 16 | B21: ='Resumen Ejecutivo'!$B$10 -> 4000000 | C21: =-'Inversión Inicial'!$B$18 -> -780000 | D21: 0 | E21: =B21+C21+D21 -> 3220000 | F21: =E21/(1+'Supuestos y CAPM'!$B$15)^16 -> 2759408 | G21: =G20+F21 -> 2740576.4
A22: Mes 17 | B22: ='Resumen Ejecutivo'!$B$10 -> 4000000 | C22: =-'Inversión Inicial'!$B$18 -> -780000 | D22: 0 | E22: =B22+C22+D22 -> 3220000 | F22: =E22/(1+'Supuestos y CAPM'!$B$15)^17 -> 2732913.7 | G22: =G21+F22 -> 5473490.1
A23: Mes 18 | B23: ='Resumen Ejecutivo'!$B$10 -> 4000000 | C23: =-'Inversión Inicial'!$B$18 -> -780000 | D23: 0 | E23: =B23+C23+D23 -> 3220000 | F23: =E23/(1+'Supuestos y CAPM'!$B$15)^18 -> 2706673.8 | G23: =G22+F23 -> 8180163.9
A24: TOTAL 18m | B24: =SUM(B5:B23) -> 72000000 | C24: =SUM(C5:C23) -> -14040000 | D24: =SUM(D5:D23) -> -44770000 | E24: =SUM(E5:E23) -> 13190000 | F24: =SUM(F5:F23) -> 8180163.9 | G24: =G23 -> 8180163.9
A26: INDICADORES FINANCIEROS
A27: Indicador | B27: Valor | C27: Fórmula / Interpretación
A28: VAN (Valor Actual Neto) | B28: =G23 -> 8180163.9 | C28: Suma de flujos descontados al Período 0 — si >0, proyecto crea valor
A29: TIR Mensual | B29: =IRR(E5:E23) -> 0.028718396 | C29: Tasa a la cual el VAN = 0. Si > tasa CAPM mensual → proyecto viable
A30: Período de Recuperación (meses) | B30: Al mes 16 comienza a recuperar | C30: Número de meses para que el flujo acumulado descontado sea positivo

Sheet Evaluación
A1: EVALUACIÓN ECONÓMICA DEL PROYECTO (18 MESES)
J2: Inversion Inicial | K2: Costo | M2: Costos Operativos Mensuales | N2: Costo | P2: Costo
A3: Concepto | B3: Monto (CLP) | C3: Observación | J3: Equipo desarrollo (7 roles × 4 meses) | K3: $ 44.720.200 | M3: Soporte técnico | N3: $ 780.000 | P3: $ 780.000
A4: Costo RRHH Total (4 meses desarrollo) | B4: ='Costos RRHH'!F12 -> 44720000 | C4: Equipo 7 personas × 4 meses (ver hoja 'Costos RRHH') | J4: Hardware lector EAN-13 | K4: $ 50.000 | M4: Cloudflare R2 (cloud) | N4: $0
A5: Costo Licencias y Hardware (inicial) | B5: ='Inversión Inicial'!B10 -> 50000 | C5: Incluye GitHub Team 4 meses + lector EAN-13 | J5: Repositorio GitHub Team | K5: $ 0 | M5: GitHub Team (mantención) | N5: $ 0
A6: Costo Total Inversión Inicial | B6: =B4+B5 -> 44770000 | C6: Monto a invertir en Período 0 (antes de iniciar operación) | J6: Cloudflare R2 (setup) | K6: $ 0 | M6: SQLite + stack open-source | N6: $ 0
A7: Costo Operativo (18 meses) | B7: ='Inversión Inicial'!B18*18 -> 14040000 | C7: Soporte post-implementación | J7: SQLite + stack tecnológico | K7: $ 0 | N7: $ 0
A8: Beneficio Mensual | B8: ='Resumen Ejecutivo'!B10 -> 4000000 | C8: Documento 0 §5: ~4% ventas = $1,6M + ahorros operacionales | J8: TOTAL | K8: $ 44.770.000 | M8: TOTAL | N8: $ 780.000/Mensual
A9: Beneficio Anual (18 meses) | B9: =B8*18 -> 72000000 | C9: Ahorro total estimado en un año de operación
A10: Ganancia Bruta Anual (Benef - Costo Op.) | B10: =B9-B7 -> 57960000 | C10: Sin considerar la inversión inicial
A11: Flujo Neto 18 meses (Ganancia - Inversión) | B11: =B10-B6 -> 13190000 | C11: Resultado neto al cabo de 18 meses
A12: VAN (18meses, descontado a CAPM) | B12: ='Flujo de Caja'!B28 -> 8180163.9 | C12: Valor presente neto usando tasa CAPM mensual
A13: TIR Mensual | B13: ='Flujo de Caja'!B29 -> 0.028718396 | C13: Si > tasa descuento mensual → proyecto financieramente viable
A14: TIR Anual equivalente | B14: =(1+B13)^12-1 -> 0.40461749 | C14: Tasa interna de retorno expresada en base anual
A15: ROI (18 meses) | B15: =B11/B6 -> 0.29461693 | C15: Rentabilidad total del proyecto en el primer año
A16: Período de recuperación (meses) | B16: ='Flujo de Caja'!B30 -> Al mes 16 comienza a recuperar | C16: Tiempo en meses para recuperar la inversión inicial descontada

Sheet Rendimiento
A1: RENDIMIENTO E INDICADORES CLAVE DEL PROYECTO
A3: Indicador | B3: Valor | C3: Interpretación
A4: Inversión Inicial | B4: ='Inversión Inicial'!B11 -> 44770000 | C4: Capital requerido antes del inicio de operaciones
A5: Costo Operativo Mensual | B5: ='Inversión Inicial'!B18 -> 780000 | C5: Soporte post-implementación
A6: Beneficio Mensual | B6: ='Resumen Ejecutivo'!B10 -> 4000000 | C6: Ahorro mensual estimado al operar el sistema
A7: Flujo Neto Mensual | B7: =B6-B5 -> 3220000 | C7: Ganancia neta operativa mensual
A8: Tasa de Descuento CAPM (mensual) | B8: ='Supuestos y CAPM'!B15 -> 0.0096945159 | C8: Costo de oportunidad ajustado al riesgo sistemático del sector
A9: Tasa de Descuento CAPM (anual) | B9: ='Supuestos y CAPM'!B14 -> 0.122742 | C9: Equivalente anual de la tasa de descuento
A10: VAN (12 meses) | B10: ='Flujo de Caja'!B28 -> 8180163.9 | C10: Valor positivo indica que el proyecto genera valor neto al inversionista
A11: TIR Mensual | B11: ='Flujo de Caja'!B29 -> 0.028718396 | C11: Rentabilidad intrínseca del proyecto (tasa que hace VAN = 0)
A12: Spread TIR − Tasa Descuento (mensual) | B12: =B11-B8 -> 0.01902388 | C12: Diferencia entre la TIR y la tasa de descuento — positivo indica viabilidad
A13: ROI (12 meses) | B13: ='Evaluación'!B15 -> 0.29461693 | C13: Retorno sobre la inversión total al cabo de 1 año
A14: Período de recuperación | B14: ='Flujo de Caja'!B30 -> Al mes 16 comienza a recuperar | C14: Meses para que el flujo acumulado descontado sea positivo
A15: Margen operacional mensual | B15: =B7/B6 -> 0.805 | C15: Proporción del beneficio que queda después de costos operativos
